duo_universal/__init__.py
duo_universal/ca_certs.pem
duo_universal/client.py
duo_universal/version.py
duo_universal-2.2.0.dist-info/licenses/LICENSE
duo_universal-2.2.0.dist-info/METADATA
duo_universal-2.2.0.dist-info/WHEEL
duo_universal-2.2.0.dist-info/top_level.txt
duo_universal-2.2.0.dist-info/RECORD
