Metadata-Version: 2.4
Name: duo_universal
Version: 2.2.0
Summary: Duo Web SDK for two-factor authentication
Home-page: https://github.com/duosecurity/duo_universal_python
Author: Duo Security, Inc.
Author-email: support@duosecurity.com
License: BSD
Classifier: Programming Language :: Python :: 3
Classifier: License :: OSI Approved :: BSD License
Requires-Python: >=3
License-File: LICENSE
Requires-Dist: PyJWT>=2.0
Requires-Dist: requests>=2.22.0
Requires-Dist: wheel>=0.35.1
Dynamic: author
Dynamic: author-email
Dynamic: classifier
Dynamic: description
Dynamic: description-content-type
Dynamic: home-page
Dynamic: license
Dynamic: license-file
Dynamic: requires-dist
Dynamic: requires-python
Dynamic: summary
